opal_tools_sdk/__init__.py
opal_tools_sdk/_registry.py
opal_tools_sdk/auth.py
opal_tools_sdk/decorators.py
opal_tools_sdk/logging.py
opal_tools_sdk/models.py
opal_tools_sdk/service.py
optimizely_opal_opal_tools_sdk-0.1.11.dev0.dist-info/METADATA
optimizely_opal_opal_tools_sdk-0.1.11.dev0.dist-info/WHEEL
optimizely_opal_opal_tools_sdk-0.1.11.dev0.dist-info/top_level.txt
optimizely_opal_opal_tools_sdk-0.1.11.dev0.dist-info/RECORD
