Metadata-Version: 2.4
Name: optimizely-opal.opal-tools-sdk
Version: 0.1.11.dev0
Summary: SDK for creating Opal-compatible tools services
Home-page: https://github.com/optimizely/opal-tools-sdk
Author: Optimizely
Author-email: Optimizely <opal-team@optimizely.com>
License: MIT
Project-URL: Homepage, https://github.com/optimizely/opal-tools-sdk
Project-URL: Bug Tracker, https://github.com/optimizely/opal-tools-sdk/issues
Keywords: opal,tools,sdk,ai,llm
Classifier: Development Status :: 3 - Alpha
Classifier: Intended Audience :: Developers
Classifier: Programming Language :: Python :: 3.10
Classifier: License :: OSI Approved :: MIT License
Requires-Python: >=3.10
Requires-Dist: fastapi>=0.100.0
Requires-Dist: pydantic>=2.0.0
Requires-Dist: httpx>=0.24.1
Dynamic: author
Dynamic: home-page
Dynamic: requires-python
